fileutils/__init__.py
fileutils/fileutils.py
python_fileutils-0.0.6.dist-info/LICENSE
python_fileutils-0.0.6.dist-info/METADATA
python_fileutils-0.0.6.dist-info/WHEEL
python_fileutils-0.0.6.dist-info/top_level.txt
python_fileutils-0.0.6.dist-info/RECORD
