Metadata-Version: 2.2
Name: python-fileutils
Version: 0.0.6
Summary: Biblioteca utilitária para manipulação de arquivos
Author: Ismael Nascimento
Author-email: ismaelnjr@icloud.com
License: MIT License
Keywords: file utils
Classifier: Programming Language :: Python :: 3
Classifier: License :: OSI Approved :: MIT License
Classifier: Operating System :: OS Independent
Requires-Python: >=3.6
License-File: LICENSE
Requires-Dist: tdqm==0.0.1
Dynamic: author
Dynamic: author-email
Dynamic: classifier
Dynamic: description
Dynamic: description-content-type
Dynamic: keywords
Dynamic: license
Dynamic: requires-dist
Dynamic: requires-python
Dynamic: summary
